fibonacci_mpu/__init__.py
fibonacci_mpu/cli.py
fibonacci_mpu/fibonacci_mpu.py
fibonacci_mpu-0.0.1.dist-info/AUTHORS.rst
fibonacci_mpu-0.0.1.dist-info/LICENSE
fibonacci_mpu-0.0.1.dist-info/METADATA
fibonacci_mpu-0.0.1.dist-info/WHEEL
fibonacci_mpu-0.0.1.dist-info/entry_points.txt
fibonacci_mpu-0.0.1.dist-info/top_level.txt
fibonacci_mpu-0.0.1.dist-info/RECORD
