Metadata-Version: 2.1
Name: fibonacci-mpu
Version: 0.0.1
Summary: First package upload
Home-page: https://github.com/MaartenUijen/fibonacci_mpu
Author: maarten_uijen
Author-email: maarten.uijen@ordina.nl
License: MIT license
Keywords: fibonacci_mpu
Platform: UNKNOWN
Classifier: Development Status :: 2 - Pre-Alpha
Classifier: Intended Audience :: Developers
Classifier: License :: OSI Approved :: MIT License
Classifier: Natural Language :: English
Classifier: Programming Language :: Python :: 3
Classifier: Programming Language :: Python :: 3.5
Classifier: Programming Language :: Python :: 3.6
Classifier: Programming Language :: Python :: 3.7
Classifier: Programming Language :: Python :: 3.8
Requires-Python: >=3.5
Requires-Dist: Click (>=7.0)
